gwtf/__init__.py
gwtf/core.py
gwtf/mcr.py
gwtf/model.py
gwtf/version.py
gwtf-0.1.0.dist-info/licenses/LICENSE
gwtf-0.1.0.dist-info/METADATA
gwtf-0.1.0.dist-info/WHEEL
gwtf-0.1.0.dist-info/top_level.txt
gwtf-0.1.0.dist-info/RECORD
