Metadata-Version: 2.4
Name: gwtf
Version: 0.1.0
Summary: Python implementation of the Water Table Fluctuation (WTF) Method
Author-email: Raoul Collenteur <raoulcollenteur@gmail.com>
Maintainer-email: Raoul Collenteur <raoulcollenteur@gmail.com>
License:                     GNU GENERAL PUBLIC LICENSE
Project-URL: Homepage, https://github.com/raoulcollenteur/gwtf
Project-URL: Documentation, https://gwtf.readthedocs.io
Project-URL: Repository, https://github.com/raoulcollenteur/gwtf
Project-URL: Issues, https://github.com/raoulcollenteur/gwtf/issues
Project-URL: Changelog, https://github.com/raoulcollenteur/gwtf/blob/main/CHANGELOG.md
Keywords: hydrology,groundwater,water table,fluctuation,wtf
Classifier: Development Status :: 3 - Alpha
Classifier: Intended Audience :: Science/Research
Classifier: License :: OSI Approved :: MIT License
Classifier: Operating System :: OS Independent
Classifier: Programming Language :: Python :: 3.10
Classifier: Programming Language :: Python :: 3.11
Classifier: Programming Language :: Python :: 3.12
Classifier: Programming Language :: Python :: 3.13
Classifier: Topic :: Scientific/Engineering :: Hydrology
Requires-Python: >=3.8
License-File: LICENSE
Requires-Dist: numpy>=1.20.0
Requires-Dist: pandas>=1.3.0
Requires-Dist: matplotlib>=3.5.0
Requires-Dist: scipy>=1.7.0
Provides-Extra: dev
Requires-Dist: pytest>=7.0.0; extra == "dev"
Requires-Dist: pytest-cov>=4.0.0; extra == "dev"
Requires-Dist: black>=22.0.0; extra == "dev"
Requires-Dist: flake8>=5.0.0; extra == "dev"
Requires-Dist: mypy>=1.0.0; extra == "dev"
Requires-Dist: pre-commit>=2.20.0; extra == "dev"
Provides-Extra: docs
Requires-Dist: sphinx>=5.0.0; extra == "docs"
Requires-Dist: sphinx-rtd-theme>=1.0.0; extra == "docs"
Requires-Dist: nbsphinx>=0.8.0; extra == "docs"
Provides-Extra: examples
Requires-Dist: jupyter>=1.0.0; extra == "examples"
Dynamic: license-file
